pavouk_ecs/__init__.py
pavouk_ecs/id_generator.py
pavouk_ecs/log.py
pavouk_ecs/setup.py
pavouk_ecs/component/__init__.py
pavouk_ecs/component/manager.py
pavouk_ecs/entity/__init__.py
pavouk_ecs/entity/manager.py
pavouk_ecs/system/__init__.py
pavouk_ecs/tests/__init__.py
pavouk_ecs/tests/component/__init__.py
pavouk_ecs/tests/component/test_component_manager.py
pavouk_ecs/tests/component/test_components.py
pavouk_ecs/tests/entity/__init__.py
pavouk_ecs/tests/entity/test_entity.py
pavouk_ecs/tests/entity/test_entity_manager.py
pavouk_ecs-0.1.0.dist-info/LICENSE
pavouk_ecs-0.1.0.dist-info/METADATA
pavouk_ecs-0.1.0.dist-info/WHEEL
pavouk_ecs-0.1.0.dist-info/top_level.txt
pavouk_ecs-0.1.0.dist-info/RECORD
