Metadata-Version: 2.1
Name: pavouk-ecs
Version: 0.1.0
Summary: ECS implementation for Python
Home-page: https://gitlab.com/ten.pavouk/pavouk-ecs.git
Author: Ten Pavouk
Author-email: ten.pavouk@gmail.com
Project-URL: Bug Tracker, https://gitlab.com/ten.pavouk/pavouk-ecs/-/issues
Classifier: Programming Language :: Python :: 3
Classifier: License :: OSI Approved :: MIT License
Classifier: Operating System :: OS Independent
Requires-Python: >=3.6
License-File: LICENSE
